{
    "data": [
        {
            "id": 1,
            "title": "1 cuidado dental canino",
            "description":"lalalalalalalalala",
            "content": "George",
            "image":"url",
            "autor": {
                "link":"perfil",
                "first_name":"Pedro",
                "last_name":"Wong"
            },
            "date": "Tue Jul 20 1999 15:17:40 GMT-0500 (hora de verano central)",
            "categories": ["alimentacion","cuidado","tips"]
        },
        {
            "id": 2,
            "title": "2 cuidado dental canino",
            "description":"lalalalalalalalala",
            "content": "Cuidar a un perro implica compromiso y atención. En general, es importante procurar una alimentación saludable para ellos, así como favorecer su actividad física y estimular su socialización. También es fundamental ofrecerle cuidados y revisiones veterinarias para controlar su estado de salud y mejorar su calidad de vida.\n\nSi se trata de un cachorro recién nacido, los cuidados del perro serán continuos, incluyendo el amamantamiento con leche materna o sustitutivo, y el destete, que se inicia a partir de las cuatro semanas de vida y de forma progresiva.\n\nMientras que, si se trata de un perro de edad más avanzada que adoptamos en casa, hay algunas indicaciones a tener en cuenta, como darle mucho cariño, seguridad y comprensión. Y en este caso, lo mejor es sacarle en paseos cortos y frecuentes para que se vaya habituando poco a poco a su nueva rutina fuera de la protectora o refugio.\n\nEs muy importante tomar conciencia de que tener una mascota implica una gran dedicación y responsabilidad. Cuando decidimos acoger a un perro en casa debemos estar dispuestos a cubrir todas sus necesidades. Esta animal requiere compromiso, mimo y tiempo. No solo se trata de abastecerle de agua y comida, sino que hay mucho más.\n\nEsos son los principales cuidados del perro que debes conocer y aplicar para favorecer su salud.\n\nAlimentación de calidad\nElegir un pienso nutritivo y darles una buena hidratación es clave para el bienestar de los perros. Hay que ofrecerles alimentos de calidad en función de su etapa de vida, según si es cachorro, adulto o senior.\n\nSi se trata de un cachorro o de un perro mayor habrá que adaptar su dieta a sus requerimientos. Lo mismo sucede si la mascota tiene alguna intolerancia, patología o necesidad alimentaria específica.\n\nEducación animal\nEnseñar a un perro es esencial para que se desarrolle satisfactoriamente. Hay que indicarle dónde hacer sus necesidades, en qué espacios, qué puede hacer y que no, y guiarlo desde el principio para inculcarle un buen aprendizaje. Eso sí, siempre desde el refuerzo positivo, evitando reñirle bruscamente o gritarle, ya que así solo conseguiremos asustarle.\n\nPor otra parte, la educación canina también implica la interacción del perro con su entorno. Nos referimos a socializarle tanto con otras personas, como con otros canes. Y en el caso de que muestre una conducta de miedo, desconfianza o de agresividad, es aconsejable consultar con un adiestrador canino para reconducir su conducta.",
            "image":"url",
            "autor": {
                "link":"perfil",
                "first_name":"Pedro",
                "last_name":"Wong"
            },
            "date": 1711412263002,
            "categories": ["alimentacion","cuidado","recetas"]
        },
        {
            "id": 3,
            "title": "3 cuidado dental canino",
            "description":"lalalalalalalalala",
            "content": "George",
            "image":"url",
            "autor": {
                "link":"perfil",
                "first_name":"Pedro",
                "last_name":"Wong"
            },
            "date": 1711412263002,
            "categories": ["alimentacion","tips","recetas"]
        },
        {
            "id": 4,
            "title": "4 cuidado dental canino",
            "description":"lalalalalalalalala",
            "content": "George",
            "image":"url",
            "autor": {
                "link":"perfil",
                "first_name":"Pedro",
                "last_name":"Wong"
            },
            "date": 1711412263002,
            "categories": ["cuidado","tips","recetas"]
        },
        {
            "id": 5,
            "title": "5 cuidado dental canino",
            "description":"lalalalalalalalala",
            "content": "George",
            "image":"url",
            "autor": {
                "link":"perfil",
                "first_name":"Pedro",
                "last_name":"Wong"
            },
            "date": 1711412263002,
            "categories": ["alimentacion"]
        },
        {
            "id": 6,
            "title": "6 cuidado dental canino",
            "description":"lalalalalalalalala",
            "content": "George",
            "image":"url",
            "autor": {
                "link":"perfil",
                "first_name":"Pedro",
                "last_name":"Wong"
            },
            "date": 1711412263002,
            "categories": ["tips","recetas"]
        },
        {
            "id": 7,
            "title": "7 cuidado dental canino",
            "description":"lalalalalalalalala",
            "content": "George",
            "image":"url",
            "autor": {
                "link":"perfil",
                "first_name":"Pedro",
                "last_name":"Wong"
            },
            "date": 1711412263002,
            "categories": ["cuidado"]
        },
        {
            "id": 8,
            "title": "8 cuidado dental canino",
            "description":"lalalalalalalalala",
            "content": "George",
            "image":"url",
            "autor": {
                "link":"perfil",
                "first_name":"Pedro",
                "last_name":"Wong"
            },
            "date": 1711412263002,
            "categories": ["recetas"]
        },
        {
            "id": 9,
            "title": "9 cuidado dental canino",
            "description":"lalalalalalalalala",
            "content": "George",
            "image":"url",
            "autor": {
                "link":"perfil",
                "first_name":"Pedro",
                "last_name":"Wong"
            },
            "date": 1711412263002,
            "categories": ["cuidado","tips"]
        },
        {
            "id": 10,
            "title": "10 cuidado dental canino",
            "description":"lalalalalalalalala",
            "content": "George",
            "image":"url",
            "autor": {
                "link":"perfil",
                "first_name":"Pedro",
                "last_name":"Wong"
            },
            "date": 1711412263002,
            "categories": ["alimentacion","cuidado","tips","recetas"]
        },
        {
            "id": 11,
            "title": "11 cuidado dental canino",
            "description":"lalalalalalalalala",
            "content": "qdwqwdqdqwdqwd\ndqwdqdqdqwdqwdqdqwdwqDQDEQEDq\ndqddwqqwddddddddddddddddddddddqdqdqdw\n\ndqwdqdqdqwdqwdqd",
            "image":"url",
            "autor": {
                "link":"perfil",
                "first_name":"Pedro",
                "last_name":"Wong"
            },
            "date": 1711412263002,
            "categories": ["tips"]
        },
        {
            "id": 12,
            "title": "12 cuidado dental canino",
            "description":"lalalalalalalalala",
            "content": "Lorem ipsum dolor sit amet consectetur adipisicing elit. Et eum accusamus velit rerum libero, fuga quaerat possimus quidem consequatur corporis voluptas, asperiores tempore nam ea modi, dolores quas inventore veritatis? Unde, incidunt ipsum. Ratione, repellat sunt. Velit, distinctio in nemo ipsum expedita \n\n impedit veniam consequuntur quae, ex nulla voluptate? Necessitatibus ducimus magnam suscipit, mollitia voluptatibus minima maxime incidunt esse expedita! Ratione nobis officia est corrupti doloremque, optio veritatis natus, magni repellendus sequi laboriosam veniam. Quos nobis\n numquam voluptas nostrum perferendis repellat, ipsum ex, nihil eos obcaecati laboriosam recusandae. Numquam, illum!\n\n\nLorem ipsum dolor sit amet consectetur adipisicing elit. Et eum accusamus velit rerum libero, fuga quaerat possimus quidem consequatur corporis voluptas, asperiores tempore nam ea modi, dolores quas inventore veritatis? Unde, incidunt ipsum. Ratione, repellat sunt. Velit, distinctio in nemo ipsum expedita \n\n impedit veniam consequuntur quae, ex nulla voluptate? Necessitatibus ducimus magnam suscipit, mollitia voluptatibus minima maxime incidunt esse expedita! Ratione nobis officia est corrupti doloremque, optio veritatis natus, magni repellendus sequi laboriosam veniam. Quos nobis\n numquam voluptas nostrum perferendis repellat, ipsum ex, nihil eos obcaecati laboriosam recusandae. Numquam, illum!",
            "image":"url",
            "autor": {
                "link":"perfil",
                "first_name":"Pedro",
                "last_name":"Wong"
            },
            "date": 1711412263002,
            "categories": ["tips","recetas"]
        }
    ]
}